[
  {"policy": "clear", "experiment": "alfred_vary_envs_sequential_pick_handtowel", "entropy_cost": 0.01, "num_actors": 10, "batch_size": 10, "seconds_between_yields": 60, "render_freq": 2000, "eval_sequential": false, "pause_actors_during_yield": false, "unroll_length": 80, "batch_replay_ratio":1.0, "replay_buffer_frames": 1.5e6, "large_file_path": "/scratch/snpowers", "comment": ""},
  {"policy": "clear", "experiment": "alfred_vary_envs_sequential_pick_handtowel", "entropy_cost": 0.01, "num_actors": 10, "batch_size": 10, "seconds_between_yields": 60, "render_freq": 2000, "eval_sequential": false, "pause_actors_during_yield": false, "unroll_length": 80, "batch_replay_ratio":1.0, "replay_buffer_frames": 1.5e6, "large_file_path": "/scratch/snpowers", "comment": ""},
  {"policy": "clear", "experiment": "alfred_vary_envs_sequential_pick_handtowel", "entropy_cost": 0.01, "num_actors": 10, "batch_size": 10, "seconds_between_yields": 60, "render_freq": 2000, "eval_sequential": false, "pause_actors_during_yield": false, "unroll_length": 80, "batch_replay_ratio":1.0, "replay_buffer_frames": 1.5e6, "large_file_path": "/scratch/snpowers", "comment": ""},

  {"policy": "ewc", "experiment": "alfred_vary_envs_sequential_pick_handtowel", "ewc_lambda": 10000, "entropy_cost": 0.01, "num_actors": 10, "batch_size": 10, "seconds_between_yields": 60, "render_freq": 2000, "eval_sequential": false, "pause_actors_during_yield": false, "unroll_length": 80, "large_file_path": "/scratch/snpowers", "comment": ""},
  {"policy": "ewc", "experiment": "alfred_vary_envs_sequential_pick_handtowel", "ewc_lambda": 10000, "entropy_cost": 0.01, "num_actors": 10, "batch_size": 10, "seconds_between_yields": 60, "render_freq": 2000, "eval_sequential": false, "pause_actors_during_yield": false, "unroll_length": 80, "large_file_path": "/scratch/snpowers", "comment": ""},
  {"policy": "ewc", "experiment": "alfred_vary_envs_sequential_pick_handtowel", "ewc_lambda": 10000, "entropy_cost": 0.01, "num_actors": 10, "batch_size": 10, "seconds_between_yields": 60, "render_freq": 2000, "eval_sequential": false, "pause_actors_during_yield": false, "unroll_length": 80, "large_file_path": "/scratch/snpowers", "comment": ""},

  {"policy": "progress_and_compress", "experiment": "alfred_vary_envs_sequential_pick_handtowel", "num_train_steps_of_progress": 1250, "ewc_lambda": 3000, "entropy_cost": 0.01, "num_actors": 10, "batch_size": 10, "seconds_between_yields": 60, "render_freq": 2000, "eval_sequential": false, "pause_actors_during_yield": false, "unroll_length": 80, "large_file_path": "/scratch/snpowers", "comment": ""},
  {"policy": "progress_and_compress", "experiment": "alfred_vary_envs_sequential_pick_handtowel", "num_train_steps_of_progress": 1250, "ewc_lambda": 3000, "entropy_cost": 0.01, "num_actors": 10, "batch_size": 10, "seconds_between_yields": 60, "render_freq": 2000, "eval_sequential": false, "pause_actors_during_yield": false, "unroll_length": 80, "large_file_path": "/scratch/snpowers", "comment": ""},
  {"policy": "progress_and_compress", "experiment": "alfred_vary_envs_sequential_pick_handtowel", "num_train_steps_of_progress": 1250, "ewc_lambda": 3000, "entropy_cost": 0.01, "num_actors": 10, "batch_size": 10, "seconds_between_yields": 60, "render_freq": 2000, "eval_sequential": false, "pause_actors_during_yield": false, "unroll_length": 80, "large_file_path": "/scratch/snpowers", "comment": ""}
]
